{
    "num_leds": 16,
    "segments": [
        {
            "start": 0,
            "end": 0,
            "color": "#00d21c",
            "mode": "CHASE_BLACKOUT",
            "signal_info": {
                "message": "ID293UI_chassisControl",
                "id": 659,
                "start": 42,
                "length": 2,
                "byte_order": "little_endian",
                "is_signed": false,
                "scale": 1,
                "offset": 0,
                "minimum": 0,
                "maximum": 3,
                "unit": null,
                "choices": {
                    "0": "PEDAL_SAFETY_OFF",
                    "1": "PEDAL_SAFETY_ON",
                    "3": "SNA"
                },
                "comment": null,
                "name": "test",
                "signal": "UI_pedalSafetyEnable"
            },
            "speed": 1,
            "reverse": false
        },
        {
            "start": 0,
            "end": 4,
            "color": "#ff0000",
            "mode": "RUNNING_LIGHTS",
            "signal_info": {
                "message": "ID239DAS_lanes",
                "id": 569,
                "start": 48,
                "length": 2,
                "byte_order": "little_endian",
                "is_signed": false,
                "scale": 1,
                "offset": 0,
                "minimum": 0,
                "maximum": 3,
                "unit": null,
                "choices": {
                    "1": "AVAILABLE",
                    "3": "BLACKLISTED",
                    "2": "FUSED",
                    "0": "REJECTED_UNAVAILABLE"
                },
                "comment": null,
                "name": "Segment 2",
                "signal": "DAS_leftLineUsage",
                "inactive_value": "AVAILABLE"
            },
            "speed": 88,
            "reverse": false
        }
    ]
}